
[
    {"id": 1, "State": "Abia State", "Capital": "Umuahia" },
    {"id": 2, "State": "Adamawa State", "Capital": "Yola" },
    {"id": 3, "State": "Akwa Ibom State", "Capital": "Uyo" },
    {"id": 4, "State": "Anambra State", "Capital": "Awka" },
    {"id": 5, "State": "Bauchi State", "Capital": "Bauchi" },
    {"id": 6, "State": "Bayelsa State", "Capital": "Yenagoa" },
    {"id": 7, "State": "Benue State", "Capital": "Makurdi" },
    {"id": 8, "State": "Borno State", "Capital": "Maiduguri" },
    {"id": 9, "State": "Cross River State", "Capital": "Calabar" },
    {"id": 10, "State": "Delta State", "Capital": "Asaba" },
    {"id": 11, "State": "Ebonyi State", "Capital": "Abakaliki" },
    {"id": 12, "State": "Edo State", "Capital": "Benin City" },
    {"id": 13, "State": "Ekiti State", "Capital": "Ado-Ekiti" },
    {"id": 14, "State": "Enugu State", "Capital": "Enugu" },
    {"id": 15, "State": "Gombe State", "Capital": "Gombe" },
    {"id": 16, "State": "Imo State", "Capital": "Owerri" },
    {"id": 17, "State": "Jigawa State", "Capital": "Dutse" },
    {"id": 18, "State": "Kaduna State", "Capital": "Kaduna" },
    {"id": 19, "State": "Kano State", "Capital": "Kano" },
    {"id": 20, "State": "Kebbi State", "Capital": "Bernin-Kebbi" },
    {"id": 21, "State": "Kogi State", "Capital": "Lokoja" },
    {"id": 22, "State": "Kwara State", "Capital": "Ilorin" },
    {"id": 23, "State": "Lagos State", "Capital": "Ikeja" },
    {"id": 24, "State": "Nasarawa State", "Capital": "Lafia" },
    {"id": 25, "State": "Niger State", "Capital": "Minna" },
    {"id": 26, "State": "Ogun State", "Capital": "Abeokuta" },
    {"id": 27, "State": "Ondo State", "Capital": "Akure" },
    {"id": 28, "State": "Osun State", "Capital": "Osogbo" },
    {"id": 29, "State": "Oyo State", "Capital": "Ibadan" },
    {"id": 30, "State": "Plateau State", "Capital": "Jos" },
    {"id": 31, "State": "Rivers State", "Capital": "Port-Harcourt" },
    {"id": 32, "State": "Sokoto State", "Capital": "Sokoto" },
    {"id": 33, "State": "Taraba State", "Capital": "Jalingo" },
    {"id": 34, "State": "Yobe State", "Capital": "Damaturu" },
    {"id": 35, "State": "Zamfara State", "Capital": "Gusau" },
    {"id": 35, "State": "FCT, Abuja", "Capital": "Abuja" }
]